[
  {
    "name": "Quantum StarHopper",
    "description": "A versatile Quantum StarHopper suitable for various missions across the galaxy.",
    "priceCents": 75000000,
    "imageUrl": "https://www.placehold.co/300x200.png?text=Quantum%20StarHopper",
    "manufacturer": "Corellian Engineering",
    "crewAmount": 4,
    "maxSpeed": "85 MGLT",
    "category": "Fighter",
    "stockQuantity": 12,
    "isActive": true,
    "isFeatured": true
  },
  {
    "name": "Nova Nebula Freighter",
    "description": "Heavy-duty freighter optimized for long-haul cargo runs.",
    "priceCents": 180000000,
    "imageUrl": "https://www.placehold.co/300x200.png?text=Nova%20Nebula",
    "manufacturer": "Kuat Drive Yards",
    "crewAmount": 8,
    "maxSpeed": "55 MGLT",
    "category": "Freighter",
    "stockQuantity": 7,
    "isActive": true,
    "isFeatured": true
  },
  {
    "name": "Solar Seraphim Shuttle",
    "description": "Elegant shuttle for short-range diplomatic transport.",
    "priceCents": 95000000,
    "imageUrl": "https://www.placehold.co/300x200.png?text=Solar%20Seraphim",
    "manufacturer": "Sienar Fleet Systems",
    "crewAmount": 2,
    "maxSpeed": "70 MGLT",
    "category": "Shuttle",
    "stockQuantity": 15,
    "isActive": true,
    "isFeatured": true
  },
  {
    "name": "Turbo Void Speeder",
    "description": "Lightweight speeder tuned for planetary surface runs.",
    "priceCents": 54000000,
    "imageUrl": "https://www.placehold.co/300x200.png?text=Turbo%20Void",
    "manufacturer": "Incom Corporation",
    "crewAmount": 1,
    "maxSpeed": "920 km/h (atmo)",
    "category": "Speeder",
    "stockQuantity": 22,
    "isActive": true
  },
  {
    "name": "Galactic Titan Cruiser",
    "description": "Medium cruiser with balanced armor and maneuverability.",
    "priceCents": 245000000,
    "imageUrl": "https://www.placehold.co/300x200.png?text=Galactic%20Titan",
    "manufacturer": "Mitsubishi Heavy Industries",
    "crewAmount": 12,
    "maxSpeed": "60 MGLT",
    "category": "Cruiser",
    "stockQuantity": 4,
    "isActive": true,
    "isFeatured": true
  },
  {
    "name": "Prototype Phoenix Capital Ship",
    "description": "Experimental capital-class dreadnought. One of a kind.",
    "priceCents": 2400000000,
    "imageUrl": "https://www.placehold.co/300x200.png?text=Prometheus%20Phoenix",
    "manufacturer": "Bradford Starworks",
    "crewAmount": 2,
    "maxSpeed": "40 MGLT",
    "category": "Capital Ship",
    "stockQuantity": 1,
    "isActive": true
  },
  {
    "name": "Stealth Odyssey Interceptor",
    "description": "Cloaked interceptor for reconnaissance and hit-and-run.",
    "priceCents": 135000000,
    "imageUrl": "https://www.placehold.co/300x200.png?text=Stealth%20Odyssey",
    "manufacturer": "Northrop Grumman",
    "crewAmount": 1,
    "maxSpeed": "110 MGLT",
    "category": "Fighter",
    "stockQuantity": 6,
    "isActive": true
  },
  {
    "name": "Cryo Horizon Transport",
    "description": "Refrigerated cargo transport for sensitive biologics.",
    "priceCents": 115000000,
    "imageUrl": "https://www.placehold.co/300x200.png?text=Cryo%20Horizon",
    "manufacturer": "Weyland-Yutani",
    "crewAmount": 6,
    "maxSpeed": "48 MGLT",
    "category": "Freighter",
    "stockQuantity": 9,
    "isActive": true
  },
  {
    "name": "Neon Pioneer Courier",
    "description": "Fast short-haul courier favored by the Outer Rim postal service.",
    "priceCents": 62000000,
    "imageUrl": "https://www.placehold.co/300x200.png?text=Neon%20Pioneer",
    "manufacturer": "Quark Systems",
    "crewAmount": 2,
    "maxSpeed": "78 MGLT",
    "category": "Shuttle",
    "stockQuantity": 18,
    "isActive": true
  },
  {
    "name": "Mark III Vanguard Runner",
    "description": "Proven mid-weight runner with above-average agility.",
    "priceCents": 88000000,
    "imageUrl": "https://www.placehold.co/300x200.png?text=Mark%20III%20Vanguard",
    "manufacturer": "Argus Shipyards",
    "crewAmount": 3,
    "maxSpeed": "92 MGLT",
    "category": "Speeder",
    "stockQuantity": 10,
    "isActive": true
  },
  {
    "name": "Heavy Infinity Guardian",
    "description": "Armored cruiser configured for fleet escort duty.",
    "priceCents": 310000000,
    "imageUrl": "https://www.placehold.co/300x200.png?text=Heavy%20Infinity",
    "manufacturer": "Lockheed Martin",
    "crewAmount": 22,
    "maxSpeed": "50 MGLT",
    "category": "Cruiser",
    "stockQuantity": 3,
    "isActive": true
  },
  {
    "name": "Alpha Serenity",
    "description": "Compact fighter with exceptional thrust-to-mass ratio.",
    "priceCents": 120000000,
    "imageUrl": "https://www.placehold.co/300x200.png?text=Alpha%20Serenity",
    "manufacturer": "Covenant Industries",
    "crewAmount": 1,
    "maxSpeed": "105 MGLT",
    "category": "Fighter",
    "stockQuantity": 8,
    "isActive": true
  },
  {
    "name": "Omega Andromeda Hauler",
    "description": "Bulk hauler for asteroid-mining operations.",
    "priceCents": 198000000,
    "imageUrl": "https://www.placehold.co/300x200.png?text=Omega%20Andromeda",
    "manufacturer": "Raven Rock Assembly",
    "crewAmount": 14,
    "maxSpeed": "42 MGLT",
    "category": "Freighter",
    "stockQuantity": 5,
    "isActive": true
  },
  {
    "name": "Scout Eclipse Jumper",
    "description": "Nimble long-range scout with an oversized fuel tank.",
    "priceCents": 72000000,
    "imageUrl": "https://www.placehold.co/300x200.png?text=Scout%20Eclipse",
    "manufacturer": "Palladium Dynamics",
    "crewAmount": 2,
    "maxSpeed": "88 MGLT",
    "category": "Shuttle",
    "stockQuantity": 11,
    "isActive": true
  },
  {
    "name": "Hyperion Zenith Capital",
    "description": "Flagship capital ship for command-and-control operations.",
    "priceCents": 2150000000,
    "imageUrl": "https://www.placehold.co/300x200.png?text=Hyperion%20Zenith",
    "manufacturer": "Boeing Defense",
    "crewAmount": 350,
    "maxSpeed": "38 MGLT",
    "category": "Capital Ship",
    "stockQuantity": 2,
    "isActive": true
  }
]
